[
  {
    "ContainingType": "Acceloka.Controllers.BookingController",
    "Method": "BookTicket",
    "RelativePath": "api/v1/book-ticket",
    "HttpMethod": "POST",
    "IsController": true,
    "Order": 0,
    "Parameters": [
      {
        "Name": "request",
        "Type": "Acceloka.Models.Request.BookTicketRequest",
        "IsRequired": true
      }
    ],
    "ReturnTypes": []
  },
  {
    "ContainingType": "Acceloka.Controllers.BookingController",
    "Method": "EditBookedTicket",
    "RelativePath": "api/v1/edit-booked-ticket/{bookedTicketId}",
    "HttpMethod": "PUT",
    "IsController": true,
    "Order": 0,
    "Parameters": [
      {
        "Name": "bookedTicketId",
        "Type": "System.Guid",
        "IsRequired": true
      },
      {
        "Name": "request",
        "Type": "Acceloka.Models.Request.EditBookedTicketRequest",
        "IsRequired": true
      }
    ],
    "ReturnTypes": []
  },
  {
    "ContainingType": "Acceloka.Controllers.TicketController",
    "Method": "GetAvailableTicket",
    "RelativePath": "api/v1/get-available-ticket",
    "HttpMethod": "GET",
    "IsController": true,
    "Order": 0,
    "Parameters": [
      {
        "Name": "CategoryName",
        "Type": "System.String",
        "IsRequired": false
      },
      {
        "Name": "TicketCode",
        "Type": "System.String",
        "IsRequired": false
      },
      {
        "Name": "TicketName",
        "Type": "System.String",
        "IsRequired": false
      },
      {
        "Name": "Price",
        "Type": "System.Nullable\u00601[[System.Decimal, System.Private.CoreLib, Version=8.0.0.0, Culture=neutral, PublicKeyToken=7cec85d7bea7798e]]",
        "IsRequired": false
      },
      {
        "Name": "DateMin",
        "Type": "System.Nullable\u00601[[System.DateTimeOffset, System.Private.CoreLib, Version=8.0.0.0, Culture=neutral, PublicKeyToken=7cec85d7bea7798e]]",
        "IsRequired": false
      },
      {
        "Name": "DateMax",
        "Type": "System.Nullable\u00601[[System.DateTimeOffset, System.Private.CoreLib, Version=8.0.0.0, Culture=neutral, PublicKeyToken=7cec85d7bea7798e]]",
        "IsRequired": false
      },
      {
        "Name": "OrderBy",
        "Type": "System.String",
        "IsRequired": false
      },
      {
        "Name": "OrderState",
        "Type": "System.String",
        "IsRequired": false
      },
      {
        "Name": "Page",
        "Type": "System.Nullable\u00601[[System.Int32, System.Private.CoreLib, Version=8.0.0.0, Culture=neutral, PublicKeyToken=7cec85d7bea7798e]]",
        "IsRequired": false
      }
    ],
    "ReturnTypes": []
  },
  {
    "ContainingType": "Acceloka.Controllers.BookingController",
    "Method": "GetBookedTicket",
    "RelativePath": "api/v1/get-booked-ticket/{bookedTicketId}",
    "HttpMethod": "GET",
    "IsController": true,
    "Order": 0,
    "Parameters": [
      {
        "Name": "bookedTicketId",
        "Type": "System.Guid",
        "IsRequired": true
      }
    ],
    "ReturnTypes": []
  },
  {
    "ContainingType": "Acceloka.Controllers.BookingController",
    "Method": "RevokeTicket",
    "RelativePath": "api/v1/revoke-ticket/{bookedTicketId}/{ticketCode}/{qty}",
    "HttpMethod": "DELETE",
    "IsController": true,
    "Order": 0,
    "Parameters": [
      {
        "Name": "bookedTicketId",
        "Type": "System.Guid",
        "IsRequired": true
      },
      {
        "Name": "ticketCode",
        "Type": "System.String",
        "IsRequired": true
      },
      {
        "Name": "qty",
        "Type": "System.Int32",
        "IsRequired": true
      }
    ],
    "ReturnTypes": []
  }
]